{
	"configurations" : 
	[
		{
			"directories" : 
			[
				{
					"build" : ".",
					"hasInstallRule" : true,
					"jsonFile" : "directory-.-Release-2ef158c7d8825610bc09.json",
					"minimumCMakeVersion" : 
					{
						"string" : "3.12"
					},
					"projectIndex" : 0,
					"source" : ".",
					"targetIndexes" : 
					[
						0,
						1,
						2,
						3,
						4
					]
				}
			],
			"name" : "Release",
			"projects" : 
			[
				{
					"directoryIndexes" : 
					[
						0
					],
					"name" : "ublox_gps",
					"targetIndexes" : 
					[
						0,
						1,
						2,
						3,
						4
					]
				}
			],
			"targets" : 
			[
				{
					"directoryIndex" : 0,
					"id" : "ublox_gps::@6890427a1f51a3e7e1df",
					"jsonFile" : "target-ublox_gps-Release-30cc1cb573750e2372bd.json",
					"name" : "ublox_gps",
					"projectIndex" : 0
				},
				{
					"directoryIndex" : 0,
					"id" : "ublox_gps_node::@6890427a1f51a3e7e1df",
					"jsonFile" : "target-ublox_gps_node-Release-8ed56961f71b87bc6df3.json",
					"name" : "ublox_gps_node",
					"projectIndex" : 0
				},
				{
					"directoryIndex" : 0,
					"id" : "ublox_gps_uninstall::@6890427a1f51a3e7e1df",
					"jsonFile" : "target-ublox_gps_uninstall-Release-c95506b6ad52913b0970.json",
					"name" : "ublox_gps_uninstall",
					"projectIndex" : 0
				},
				{
					"directoryIndex" : 0,
					"id" : "ublox_logger::@6890427a1f51a3e7e1df",
					"jsonFile" : "target-ublox_logger-Release-19a61adb382d2e90bada.json",
					"name" : "ublox_logger",
					"projectIndex" : 0
				},
				{
					"directoryIndex" : 0,
					"id" : "uninstall::@6890427a1f51a3e7e1df",
					"jsonFile" : "target-uninstall-Release-a7655a7d67a169be6ca2.json",
					"name" : "uninstall",
					"projectIndex" : 0
				}
			]
		}
	],
	"kind" : "codemodel",
	"paths" : 
	{
		"build" : "/home/ssc/SCV/build/ublox_gps",
		"source" : "/home/ssc/SCV/src/sensor_pkg/ublox/ublox_gps"
	},
	"version" : 
	{
		"major" : 2,
		"minor" : 3
	}
}
