{
	"artifacts" : 
	[
		{
			"path" : "libublox_msgs__rosidl_typesupport_introspection_cpp.so"
		}
	],
	"backtrace" : 5,
	"backtraceGraph" : 
	{
		"commands" : 
		[
			"add_library",
			"include",
			"ament_execute_extensions",
			"rosidl_generate_interfaces",
			"_install",
			"ament_cmake_symlink_install_targets",
			"install",
			"target_link_libraries",
			"add_dependencies",
			"add_compile_options",
			"add_definitions",
			"find_package",
			"target_include_directories",
			"set_property"
		],
		"files" : 
		[
			"/opt/ros/humble/share/rosidl_typesupport_introspection_cpp/cmake/rosidl_typesupport_introspection_cpp_generate_interfaces.cmake",
			"/opt/ros/humble/share/ament_cmake_core/cmake/core/ament_execute_extensions.cmake",
			"/opt/ros/humble/share/rosidl_cmake/cmake/rosidl_generate_interfaces.cmake",
			"CMakeLists.txt",
			"/opt/ros/humble/share/ament_cmake_core/cmake/symlink_install/ament_cmake_symlink_install_targets.cmake",
			"/opt/ros/humble/share/ament_cmake_core/cmake/symlink_install/install.cmake",
			"/opt/ros/humble/share/rosidl_generator_cpp/cmake/rosidl_generator_cpp_generate_interfaces.cmake",
			"/opt/ros/humble/share/ament_cmake_ros/cmake/ament_cmake_ros-extras.cmake",
			"/opt/ros/humble/share/ament_cmake_ros/cmake/ament_cmake_rosConfig.cmake"
		],
		"nodes" : 
		[
			{
				"file" : 3
			},
			{
				"command" : 3,
				"file" : 3,
				"line" : 104,
				"parent" : 0
			},
			{
				"command" : 2,
				"file" : 2,
				"line" : 286,
				"parent" : 1
			},
			{
				"command" : 1,
				"file" : 1,
				"line" : 48,
				"parent" : 2
			},
			{
				"file" : 0,
				"parent" : 3
			},
			{
				"command" : 0,
				"file" : 0,
				"line" : 93,
				"parent" : 4
			},
			{
				"command" : 6,
				"file" : 0,
				"line" : 146,
				"parent" : 4
			},
			{
				"command" : 5,
				"file" : 5,
				"line" : 37,
				"parent" : 6
			},
			{
				"command" : 4,
				"file" : 4,
				"line" : 50,
				"parent" : 7
			},
			{
				"command" : 7,
				"file" : 0,
				"line" : 128,
				"parent" : 4
			},
			{
				"command" : 7,
				"file" : 0,
				"line" : 128,
				"parent" : 4
			},
			{
				"command" : 7,
				"file" : 0,
				"line" : 128,
				"parent" : 4
			},
			{
				"command" : 7,
				"file" : 0,
				"line" : 128,
				"parent" : 4
			},
			{
				"command" : 7,
				"file" : 0,
				"line" : 121,
				"parent" : 4
			},
			{
				"command" : 1,
				"file" : 1,
				"line" : 48,
				"parent" : 2
			},
			{
				"file" : 6,
				"parent" : 14
			},
			{
				"command" : 8,
				"file" : 6,
				"line" : 139,
				"parent" : 15
			},
			{
				"command" : 9,
				"file" : 3,
				"line" : 10,
				"parent" : 0
			},
			{
				"command" : 7,
				"file" : 0,
				"line" : 117,
				"parent" : 4
			},
			{
				"command" : 11,
				"file" : 3,
				"line" : 13,
				"parent" : 0
			},
			{
				"file" : 8,
				"parent" : 19
			},
			{
				"command" : 1,
				"file" : 8,
				"line" : 41,
				"parent" : 20
			},
			{
				"file" : 7,
				"parent" : 21
			},
			{
				"command" : 10,
				"file" : 7,
				"line" : 25,
				"parent" : 22
			},
			{
				"command" : 12,
				"file" : 0,
				"line" : 111,
				"parent" : 4
			},
			{
				"command" : 13,
				"file" : 0,
				"line" : 103,
				"parent" : 4
			}
		]
	},
	"compileGroups" : 
	[
		{
			"compileCommandFragments" : 
			[
				{
					"fragment" : "-O3 -DNDEBUG -fPIC"
				},
				{
					"backtrace" : 17,
					"fragment" : "-Wall"
				},
				{
					"backtrace" : 17,
					"fragment" : "-Wextra"
				},
				{
					"backtrace" : 17,
					"fragment" : "-Wpedantic"
				}
			],
			"defines" : 
			[
				{
					"backtrace" : 18,
					"define" : "RCUTILS_ENABLE_FAULT_INJECTION"
				},
				{
					"define" : "ROSIDL_TYPESUPPORT_INTROSPECTION_CPP_BUILDING_DLL"
				},
				{
					"backtrace" : 23,
					"define" : "ROS_PACKAGE_NAME=\"ublox_msgs\""
				}
			],
			"includes" : 
			[
				{
					"backtrace" : 24,
					"path" : "/home/scv/SCV/build/ublox_msgs/rosidl_typesupport_introspection_cpp"
				},
				{
					"backtrace" : 18,
					"path" : "/home/scv/SCV/build/ublox_msgs/rosidl_generator_cpp"
				},
				{
					"backtrace" : 18,
					"isSystem" : true,
					"path" : "/opt/ros/humble/include/sensor_msgs"
				},
				{
					"backtrace" : 18,
					"isSystem" : true,
					"path" : "/opt/ros/humble/include/builtin_interfaces"
				},
				{
					"backtrace" : 18,
					"isSystem" : true,
					"path" : "/opt/ros/humble/include/rosidl_runtime_cpp"
				},
				{
					"backtrace" : 18,
					"isSystem" : true,
					"path" : "/opt/ros/humble/include/rosidl_runtime_c"
				},
				{
					"backtrace" : 18,
					"isSystem" : true,
					"path" : "/opt/ros/humble/include/rcutils"
				},
				{
					"backtrace" : 18,
					"isSystem" : true,
					"path" : "/opt/ros/humble/include/rosidl_typesupport_interface"
				},
				{
					"backtrace" : 18,
					"isSystem" : true,
					"path" : "/opt/ros/humble/include/geometry_msgs"
				},
				{
					"backtrace" : 18,
					"isSystem" : true,
					"path" : "/opt/ros/humble/include/std_msgs"
				},
				{
					"backtrace" : 13,
					"isSystem" : true,
					"path" : "/opt/ros/humble/include/rosidl_typesupport_introspection_cpp"
				},
				{
					"backtrace" : 13,
					"isSystem" : true,
					"path" : "/opt/ros/humble/include/rosidl_typesupport_introspection_c"
				}
			],
			"language" : "CXX",
			"languageStandard" : 
			{
				"backtraces" : 
				[
					25
				],
				"standard" : "17"
			},
			"sourceIndexes" : 
			[
				82,
				83,
				84,
				85,
				86,
				87,
				88,
				89,
				90,
				91,
				92,
				93,
				94,
				95,
				96,
				97,
				98,
				99,
				100,
				101,
				102,
				103,
				104,
				105,
				106,
				107,
				108,
				109,
				110,
				111,
				112,
				113,
				114,
				115,
				116,
				117,
				118,
				119,
				120,
				121,
				122,
				123,
				124,
				125,
				126,
				127,
				128,
				129,
				130,
				131,
				132,
				133,
				134,
				135,
				136,
				137,
				138,
				139,
				140,
				141,
				142,
				143,
				144,
				145,
				146,
				147,
				148,
				149,
				150,
				151,
				152,
				153,
				154,
				155,
				156,
				157,
				158,
				159,
				160,
				161,
				162,
				163
			]
		}
	],
	"dependencies" : 
	[
		{
			"backtrace" : 16,
			"id" : "ublox_msgs__cpp::@6890427a1f51a3e7e1df"
		}
	],
	"id" : "ublox_msgs__rosidl_typesupport_introspection_cpp::@6890427a1f51a3e7e1df",
	"install" : 
	{
		"destinations" : 
		[
			{
				"backtrace" : 8,
				"path" : "lib"
			},
			{
				"backtrace" : 8,
				"path" : "lib"
			}
		],
		"prefix" : 
		{
			"path" : "/home/scv/SCV/install/ublox_msgs"
		}
	},
	"link" : 
	{
		"commandFragments" : 
		[
			{
				"fragment" : "",
				"role" : "flags"
			},
			{
				"fragment" : "-Wl,-rpath,/opt/ros/humble/lib:",
				"role" : "libraries"
			},
			{
				"backtrace" : 9,
				"fragment" : "/opt/ros/humble/lib/libsensor_msgs__rosidl_typesupport_introspection_cpp.so",
				"role" : "libraries"
			},
			{
				"backtrace" : 10,
				"fragment" : "/opt/ros/humble/lib/libgeometry_msgs__rosidl_typesupport_introspection_cpp.so",
				"role" : "libraries"
			},
			{
				"backtrace" : 11,
				"fragment" : "/opt/ros/humble/lib/libstd_msgs__rosidl_typesupport_introspection_cpp.so",
				"role" : "libraries"
			},
			{
				"backtrace" : 12,
				"fragment" : "/opt/ros/humble/lib/libbuiltin_interfaces__rosidl_typesupport_introspection_cpp.so",
				"role" : "libraries"
			},
			{
				"backtrace" : 13,
				"fragment" : "/opt/ros/humble/lib/librosidl_typesupport_introspection_cpp.so",
				"role" : "libraries"
			},
			{
				"fragment" : "/opt/ros/humble/lib/librosidl_typesupport_introspection_c.so",
				"role" : "libraries"
			},
			{
				"backtrace" : 13,
				"fragment" : "/opt/ros/humble/lib/librosidl_runtime_c.so",
				"role" : "libraries"
			},
			{
				"fragment" : "/opt/ros/humble/lib/librcutils.so",
				"role" : "libraries"
			},
			{
				"fragment" : "-ldl",
				"role" : "libraries"
			}
		],
		"language" : "CXX"
	},
	"name" : "ublox_msgs__rosidl_typesupport_introspection_cpp",
	"nameOnDisk" : "libublox_msgs__rosidl_typesupport_introspection_cpp.so",
	"paths" : 
	{
		"build" : ".",
		"source" : "."
	},
	"sourceGroups" : 
	[
		{
			"name" : "Header Files",
			"sourceIndexes" : 
			[
				0,
				1,
				2,
				3,
				4,
				5,
				6,
				7,
				8,
				9,
				10,
				11,
				12,
				13,
				14,
				15,
				16,
				17,
				18,
				19,
				20,
				21,
				22,
				23,
				24,
				25,
				26,
				27,
				28,
				29,
				30,
				31,
				32,
				33,
				34,
				35,
				36,
				37,
				38,
				39,
				40,
				41,
				42,
				43,
				44,
				45,
				46,
				47,
				48,
				49,
				50,
				51,
				52,
				53,
				54,
				55,
				56,
				57,
				58,
				59,
				60,
				61,
				62,
				63,
				64,
				65,
				66,
				67,
				68,
				69,
				70,
				71,
				72,
				73,
				74,
				75,
				76,
				77,
				78,
				79,
				80,
				81
			]
		},
		{
			"name" : "Source Files",
			"sourceIndexes" : 
			[
				82,
				83,
				84,
				85,
				86,
				87,
				88,
				89,
				90,
				91,
				92,
				93,
				94,
				95,
				96,
				97,
				98,
				99,
				100,
				101,
				102,
				103,
				104,
				105,
				106,
				107,
				108,
				109,
				110,
				111,
				112,
				113,
				114,
				115,
				116,
				117,
				118,
				119,
				120,
				121,
				122,
				123,
				124,
				125,
				126,
				127,
				128,
				129,
				130,
				131,
				132,
				133,
				134,
				135,
				136,
				137,
				138,
				139,
				140,
				141,
				142,
				143,
				144,
				145,
				146,
				147,
				148,
				149,
				150,
				151,
				152,
				153,
				154,
				155,
				156,
				157,
				158,
				159,
				160,
				161,
				162,
				163
			]
		},
		{
			"name" : "CMake Rules",
			"sourceIndexes" : 
			[
				164
			]
		}
	],
	"sources" : 
	[
		{
			"backtrace" : 5,
			"isGenerated" : true,
			"path" : "/home/scv/SCV/build/ublox_msgs/rosidl_typesupport_introspection_cpp/ublox_msgs/msg/detail/ack__rosidl_typesupport_introspection_cpp.hpp",
			"sourceGroupIndex" : 0
		},
		{
			"backtrace" : 5,
			"isGenerated" : true,
			"path" : "/home/scv/SCV/build/ublox_msgs/rosidl_typesupport_introspection_cpp/ublox_msgs/msg/detail/aid_alm__rosidl_typesupport_introspection_cpp.hpp",
			"sourceGroupIndex" : 0
		},
		{
			"backtrace" : 5,
			"isGenerated" : true,
			"path" : "/home/scv/SCV/build/ublox_msgs/rosidl_typesupport_introspection_cpp/ublox_msgs/msg/detail/aid_eph__rosidl_typesupport_introspection_cpp.hpp",
			"sourceGroupIndex" : 0
		},
		{
			"backtrace" : 5,
			"isGenerated" : true,
			"path" : "/home/scv/SCV/build/ublox_msgs/rosidl_typesupport_introspection_cpp/ublox_msgs/msg/detail/aid_hui__rosidl_typesupport_introspection_cpp.hpp",
			"sourceGroupIndex" : 0
		},
		{
			"backtrace" : 5,
			"isGenerated" : true,
			"path" : "/home/scv/SCV/build/ublox_msgs/rosidl_typesupport_introspection_cpp/ublox_msgs/msg/detail/cfg_ant__rosidl_typesupport_introspection_cpp.hpp",
			"sourceGroupIndex" : 0
		},
		{
			"backtrace" : 5,
			"isGenerated" : true,
			"path" : "/home/scv/SCV/build/ublox_msgs/rosidl_typesupport_introspection_cpp/ublox_msgs/msg/detail/cfg_cfg__rosidl_typesupport_introspection_cpp.hpp",
			"sourceGroupIndex" : 0
		},
		{
			"backtrace" : 5,
			"isGenerated" : true,
			"path" : "/home/scv/SCV/build/ublox_msgs/rosidl_typesupport_introspection_cpp/ublox_msgs/msg/detail/cfg_dat__rosidl_typesupport_introspection_cpp.hpp",
			"sourceGroupIndex" : 0
		},
		{
			"backtrace" : 5,
			"isGenerated" : true,
			"path" : "/home/scv/SCV/build/ublox_msgs/rosidl_typesupport_introspection_cpp/ublox_msgs/msg/detail/cfg_dgnss__rosidl_typesupport_introspection_cpp.hpp",
			"sourceGroupIndex" : 0
		},
		{
			"backtrace" : 5,
			"isGenerated" : true,
			"path" : "/home/scv/SCV/build/ublox_msgs/rosidl_typesupport_introspection_cpp/ublox_msgs/msg/detail/cfg_gnss_block__rosidl_typesupport_introspection_cpp.hpp",
			"sourceGroupIndex" : 0
		},
		{
			"backtrace" : 5,
			"isGenerated" : true,
			"path" : "/home/scv/SCV/build/ublox_msgs/rosidl_typesupport_introspection_cpp/ublox_msgs/msg/detail/cfg_gnss__rosidl_typesupport_introspection_cpp.hpp",
			"sourceGroupIndex" : 0
		},
		{
			"backtrace" : 5,
			"isGenerated" : true,
			"path" : "/home/scv/SCV/build/ublox_msgs/rosidl_typesupport_introspection_cpp/ublox_msgs/msg/detail/cfg_hnr__rosidl_typesupport_introspection_cpp.hpp",
			"sourceGroupIndex" : 0
		},
		{
			"backtrace" : 5,
			"isGenerated" : true,
			"path" : "/home/scv/SCV/build/ublox_msgs/rosidl_typesupport_introspection_cpp/ublox_msgs/msg/detail/cfg_inf_block__rosidl_typesupport_introspection_cpp.hpp",
			"sourceGroupIndex" : 0
		},
		{
			"backtrace" : 5,
			"isGenerated" : true,
			"path" : "/home/scv/SCV/build/ublox_msgs/rosidl_typesupport_introspection_cpp/ublox_msgs/msg/detail/cfg_inf__rosidl_typesupport_introspection_cpp.hpp",
			"sourceGroupIndex" : 0
		},
		{
			"backtrace" : 5,
			"isGenerated" : true,
			"path" : "/home/scv/SCV/build/ublox_msgs/rosidl_typesupport_introspection_cpp/ublox_msgs/msg/detail/cfg_msg__rosidl_typesupport_introspection_cpp.hpp",
			"sourceGroupIndex" : 0
		},
		{
			"backtrace" : 5,
			"isGenerated" : true,
			"path" : "/home/scv/SCV/build/ublox_msgs/rosidl_typesupport_introspection_cpp/ublox_msgs/msg/detail/cfg_nav5__rosidl_typesupport_introspection_cpp.hpp",
			"sourceGroupIndex" : 0
		},
		{
			"backtrace" : 5,
			"isGenerated" : true,
			"path" : "/home/scv/SCV/build/ublox_msgs/rosidl_typesupport_introspection_cpp/ublox_msgs/msg/detail/cfg_navx5__rosidl_typesupport_introspection_cpp.hpp",
			"sourceGroupIndex" : 0
		},
		{
			"backtrace" : 5,
			"isGenerated" : true,
			"path" : "/home/scv/SCV/build/ublox_msgs/rosidl_typesupport_introspection_cpp/ublox_msgs/msg/detail/cfg_nmea6__rosidl_typesupport_introspection_cpp.hpp",
			"sourceGroupIndex" : 0
		},
		{
			"backtrace" : 5,
			"isGenerated" : true,
			"path" : "/home/scv/SCV/build/ublox_msgs/rosidl_typesupport_introspection_cpp/ublox_msgs/msg/detail/cfg_nmea7__rosidl_typesupport_introspection_cpp.hpp",
			"sourceGroupIndex" : 0
		},
		{
			"backtrace" : 5,
			"isGenerated" : true,
			"path" : "/home/scv/SCV/build/ublox_msgs/rosidl_typesupport_introspection_cpp/ublox_msgs/msg/detail/cfg_nmea__rosidl_typesupport_introspection_cpp.hpp",
			"sourceGroupIndex" : 0
		},
		{
			"backtrace" : 5,
			"isGenerated" : true,
			"path" : "/home/scv/SCV/build/ublox_msgs/rosidl_typesupport_introspection_cpp/ublox_msgs/msg/detail/cfg_prt__rosidl_typesupport_introspection_cpp.hpp",
			"sourceGroupIndex" : 0
		},
		{
			"backtrace" : 5,
			"isGenerated" : true,
			"path" : "/home/scv/SCV/build/ublox_msgs/rosidl_typesupport_introspection_cpp/ublox_msgs/msg/detail/cfg_rate__rosidl_typesupport_introspection_cpp.hpp",
			"sourceGroupIndex" : 0
		},
		{
			"backtrace" : 5,
			"isGenerated" : true,
			"path" : "/home/scv/SCV/build/ublox_msgs/rosidl_typesupport_introspection_cpp/ublox_msgs/msg/detail/cfg_rst__rosidl_typesupport_introspection_cpp.hpp",
			"sourceGroupIndex" : 0
		},
		{
			"backtrace" : 5,
			"isGenerated" : true,
			"path" : "/home/scv/SCV/build/ublox_msgs/rosidl_typesupport_introspection_cpp/ublox_msgs/msg/detail/cfg_sbas__rosidl_typesupport_introspection_cpp.hpp",
			"sourceGroupIndex" : 0
		},
		{
			"backtrace" : 5,
			"isGenerated" : true,
			"path" : "/home/scv/SCV/build/ublox_msgs/rosidl_typesupport_introspection_cpp/ublox_msgs/msg/detail/cfg_tmode3__rosidl_typesupport_introspection_cpp.hpp",
			"sourceGroupIndex" : 0
		},
		{
			"backtrace" : 5,
			"isGenerated" : true,
			"path" : "/home/scv/SCV/build/ublox_msgs/rosidl_typesupport_introspection_cpp/ublox_msgs/msg/detail/cfg_usb__rosidl_typesupport_introspection_cpp.hpp",
			"sourceGroupIndex" : 0
		},
		{
			"backtrace" : 5,
			"isGenerated" : true,
			"path" : "/home/scv/SCV/build/ublox_msgs/rosidl_typesupport_introspection_cpp/ublox_msgs/msg/detail/cfg_valdel__rosidl_typesupport_introspection_cpp.hpp",
			"sourceGroupIndex" : 0
		},
		{
			"backtrace" : 5,
			"isGenerated" : true,
			"path" : "/home/scv/SCV/build/ublox_msgs/rosidl_typesupport_introspection_cpp/ublox_msgs/msg/detail/cfg_valget__rosidl_typesupport_introspection_cpp.hpp",
			"sourceGroupIndex" : 0
		},
		{
			"backtrace" : 5,
			"isGenerated" : true,
			"path" : "/home/scv/SCV/build/ublox_msgs/rosidl_typesupport_introspection_cpp/ublox_msgs/msg/detail/cfg_valset__rosidl_typesupport_introspection_cpp.hpp",
			"sourceGroupIndex" : 0
		},
		{
			"backtrace" : 5,
			"isGenerated" : true,
			"path" : "/home/scv/SCV/build/ublox_msgs/rosidl_typesupport_introspection_cpp/ublox_msgs/msg/detail/cfg_valset_cfgdata__rosidl_typesupport_introspection_cpp.hpp",
			"sourceGroupIndex" : 0
		},
		{
			"backtrace" : 5,
			"isGenerated" : true,
			"path" : "/home/scv/SCV/build/ublox_msgs/rosidl_typesupport_introspection_cpp/ublox_msgs/msg/detail/esf_ins__rosidl_typesupport_introspection_cpp.hpp",
			"sourceGroupIndex" : 0
		},
		{
			"backtrace" : 5,
			"isGenerated" : true,
			"path" : "/home/scv/SCV/build/ublox_msgs/rosidl_typesupport_introspection_cpp/ublox_msgs/msg/detail/esf_meas__rosidl_typesupport_introspection_cpp.hpp",
			"sourceGroupIndex" : 0
		},
		{
			"backtrace" : 5,
			"isGenerated" : true,
			"path" : "/home/scv/SCV/build/ublox_msgs/rosidl_typesupport_introspection_cpp/ublox_msgs/msg/detail/esf_raw_block__rosidl_typesupport_introspection_cpp.hpp",
			"sourceGroupIndex" : 0
		},
		{
			"backtrace" : 5,
			"isGenerated" : true,
			"path" : "/home/scv/SCV/build/ublox_msgs/rosidl_typesupport_introspection_cpp/ublox_msgs/msg/detail/esf_raw__rosidl_typesupport_introspection_cpp.hpp",
			"sourceGroupIndex" : 0
		},
		{
			"backtrace" : 5,
			"isGenerated" : true,
			"path" : "/home/scv/SCV/build/ublox_msgs/rosidl_typesupport_introspection_cpp/ublox_msgs/msg/detail/esf_status__rosidl_typesupport_introspection_cpp.hpp",
			"sourceGroupIndex" : 0
		},
		{
			"backtrace" : 5,
			"isGenerated" : true,
			"path" : "/home/scv/SCV/build/ublox_msgs/rosidl_typesupport_introspection_cpp/ublox_msgs/msg/detail/esf_status_sens__rosidl_typesupport_introspection_cpp.hpp",
			"sourceGroupIndex" : 0
		},
		{
			"backtrace" : 5,
			"isGenerated" : true,
			"path" : "/home/scv/SCV/build/ublox_msgs/rosidl_typesupport_introspection_cpp/ublox_msgs/msg/detail/hnr_pvt__rosidl_typesupport_introspection_cpp.hpp",
			"sourceGroupIndex" : 0
		},
		{
			"backtrace" : 5,
			"isGenerated" : true,
			"path" : "/home/scv/SCV/build/ublox_msgs/rosidl_typesupport_introspection_cpp/ublox_msgs/msg/detail/inf__rosidl_typesupport_introspection_cpp.hpp",
			"sourceGroupIndex" : 0
		},
		{
			"backtrace" : 5,
			"isGenerated" : true,
			"path" : "/home/scv/SCV/build/ublox_msgs/rosidl_typesupport_introspection_cpp/ublox_msgs/msg/detail/mga_gal__rosidl_typesupport_introspection_cpp.hpp",
			"sourceGroupIndex" : 0
		},
		{
			"backtrace" : 5,
			"isGenerated" : true,
			"path" : "/home/scv/SCV/build/ublox_msgs/rosidl_typesupport_introspection_cpp/ublox_msgs/msg/detail/mon_gnss__rosidl_typesupport_introspection_cpp.hpp",
			"sourceGroupIndex" : 0
		},
		{
			"backtrace" : 5,
			"isGenerated" : true,
			"path" : "/home/scv/SCV/build/ublox_msgs/rosidl_typesupport_introspection_cpp/ublox_msgs/msg/detail/mon_hw6__rosidl_typesupport_introspection_cpp.hpp",
			"sourceGroupIndex" : 0
		},
		{
			"backtrace" : 5,
			"isGenerated" : true,
			"path" : "/home/scv/SCV/build/ublox_msgs/rosidl_typesupport_introspection_cpp/ublox_msgs/msg/detail/mon_hw__rosidl_typesupport_introspection_cpp.hpp",
			"sourceGroupIndex" : 0
		},
		{
			"backtrace" : 5,
			"isGenerated" : true,
			"path" : "/home/scv/SCV/build/ublox_msgs/rosidl_typesupport_introspection_cpp/ublox_msgs/msg/detail/mon_ver_extension__rosidl_typesupport_introspection_cpp.hpp",
			"sourceGroupIndex" : 0
		},
		{
			"backtrace" : 5,
			"isGenerated" : true,
			"path" : "/home/scv/SCV/build/ublox_msgs/rosidl_typesupport_introspection_cpp/ublox_msgs/msg/detail/mon_ver__rosidl_typesupport_introspection_cpp.hpp",
			"sourceGroupIndex" : 0
		},
		{
			"backtrace" : 5,
			"isGenerated" : true,
			"path" : "/home/scv/SCV/build/ublox_msgs/rosidl_typesupport_introspection_cpp/ublox_msgs/msg/detail/nav_att__rosidl_typesupport_introspection_cpp.hpp",
			"sourceGroupIndex" : 0
		},
		{
			"backtrace" : 5,
			"isGenerated" : true,
			"path" : "/home/scv/SCV/build/ublox_msgs/rosidl_typesupport_introspection_cpp/ublox_msgs/msg/detail/nav_clock__rosidl_typesupport_introspection_cpp.hpp",
			"sourceGroupIndex" : 0
		},
		{
			"backtrace" : 5,
			"isGenerated" : true,
			"path" : "/home/scv/SCV/build/ublox_msgs/rosidl_typesupport_introspection_cpp/ublox_msgs/msg/detail/nav_cov__rosidl_typesupport_introspection_cpp.hpp",
			"sourceGroupIndex" : 0
		},
		{
			"backtrace" : 5,
			"isGenerated" : true,
			"path" : "/home/scv/SCV/build/ublox_msgs/rosidl_typesupport_introspection_cpp/ublox_msgs/msg/detail/nav_dgps__rosidl_typesupport_introspection_cpp.hpp",
			"sourceGroupIndex" : 0
		},
		{
			"backtrace" : 5,
			"isGenerated" : true,
			"path" : "/home/scv/SCV/build/ublox_msgs/rosidl_typesupport_introspection_cpp/ublox_msgs/msg/detail/nav_dgpssv__rosidl_typesupport_introspection_cpp.hpp",
			"sourceGroupIndex" : 0
		},
		{
			"backtrace" : 5,
			"isGenerated" : true,
			"path" : "/home/scv/SCV/build/ublox_msgs/rosidl_typesupport_introspection_cpp/ublox_msgs/msg/detail/nav_dop__rosidl_typesupport_introspection_cpp.hpp",
			"sourceGroupIndex" : 0
		},
		{
			"backtrace" : 5,
			"isGenerated" : true,
			"path" : "/home/scv/SCV/build/ublox_msgs/rosidl_typesupport_introspection_cpp/ublox_msgs/msg/detail/nav_posecef__rosidl_typesupport_introspection_cpp.hpp",
			"sourceGroupIndex" : 0
		},
		{
			"backtrace" : 5,
			"isGenerated" : true,
			"path" : "/home/scv/SCV/build/ublox_msgs/rosidl_typesupport_introspection_cpp/ublox_msgs/msg/detail/nav_posllh__rosidl_typesupport_introspection_cpp.hpp",
			"sourceGroupIndex" : 0
		},
		{
			"backtrace" : 5,
			"isGenerated" : true,
			"path" : "/home/scv/SCV/build/ublox_msgs/rosidl_typesupport_introspection_cpp/ublox_msgs/msg/detail/nav_pvt7__rosidl_typesupport_introspection_cpp.hpp",
			"sourceGroupIndex" : 0
		},
		{
			"backtrace" : 5,
			"isGenerated" : true,
			"path" : "/home/scv/SCV/build/ublox_msgs/rosidl_typesupport_introspection_cpp/ublox_msgs/msg/detail/nav_pvt__rosidl_typesupport_introspection_cpp.hpp",
			"sourceGroupIndex" : 0
		},
		{
			"backtrace" : 5,
			"isGenerated" : true,
			"path" : "/home/scv/SCV/build/ublox_msgs/rosidl_typesupport_introspection_cpp/ublox_msgs/msg/detail/nav_relposned9__rosidl_typesupport_introspection_cpp.hpp",
			"sourceGroupIndex" : 0
		},
		{
			"backtrace" : 5,
			"isGenerated" : true,
			"path" : "/home/scv/SCV/build/ublox_msgs/rosidl_typesupport_introspection_cpp/ublox_msgs/msg/detail/nav_relposned__rosidl_typesupport_introspection_cpp.hpp",
			"sourceGroupIndex" : 0
		},
		{
			"backtrace" : 5,
			"isGenerated" : true,
			"path" : "/home/scv/SCV/build/ublox_msgs/rosidl_typesupport_introspection_cpp/ublox_msgs/msg/detail/nav_sat__rosidl_typesupport_introspection_cpp.hpp",
			"sourceGroupIndex" : 0
		},
		{
			"backtrace" : 5,
			"isGenerated" : true,
			"path" : "/home/scv/SCV/build/ublox_msgs/rosidl_typesupport_introspection_cpp/ublox_msgs/msg/detail/nav_satsv__rosidl_typesupport_introspection_cpp.hpp",
			"sourceGroupIndex" : 0
		},
		{
			"backtrace" : 5,
			"isGenerated" : true,
			"path" : "/home/scv/SCV/build/ublox_msgs/rosidl_typesupport_introspection_cpp/ublox_msgs/msg/detail/nav_sbas__rosidl_typesupport_introspection_cpp.hpp",
			"sourceGroupIndex" : 0
		},
		{
			"backtrace" : 5,
			"isGenerated" : true,
			"path" : "/home/scv/SCV/build/ublox_msgs/rosidl_typesupport_introspection_cpp/ublox_msgs/msg/detail/nav_sbassv__rosidl_typesupport_introspection_cpp.hpp",
			"sourceGroupIndex" : 0
		},
		{
			"backtrace" : 5,
			"isGenerated" : true,
			"path" : "/home/scv/SCV/build/ublox_msgs/rosidl_typesupport_introspection_cpp/ublox_msgs/msg/detail/nav_sol__rosidl_typesupport_introspection_cpp.hpp",
			"sourceGroupIndex" : 0
		},
		{
			"backtrace" : 5,
			"isGenerated" : true,
			"path" : "/home/scv/SCV/build/ublox_msgs/rosidl_typesupport_introspection_cpp/ublox_msgs/msg/detail/nav_status__rosidl_typesupport_introspection_cpp.hpp",
			"sourceGroupIndex" : 0
		},
		{
			"backtrace" : 5,
			"isGenerated" : true,
			"path" : "/home/scv/SCV/build/ublox_msgs/rosidl_typesupport_introspection_cpp/ublox_msgs/msg/detail/nav_svinfo__rosidl_typesupport_introspection_cpp.hpp",
			"sourceGroupIndex" : 0
		},
		{
			"backtrace" : 5,
			"isGenerated" : true,
			"path" : "/home/scv/SCV/build/ublox_msgs/rosidl_typesupport_introspection_cpp/ublox_msgs/msg/detail/nav_svinfosv__rosidl_typesupport_introspection_cpp.hpp",
			"sourceGroupIndex" : 0
		},
		{
			"backtrace" : 5,
			"isGenerated" : true,
			"path" : "/home/scv/SCV/build/ublox_msgs/rosidl_typesupport_introspection_cpp/ublox_msgs/msg/detail/nav_svin__rosidl_typesupport_introspection_cpp.hpp",
			"sourceGroupIndex" : 0
		},
		{
			"backtrace" : 5,
			"isGenerated" : true,
			"path" : "/home/scv/SCV/build/ublox_msgs/rosidl_typesupport_introspection_cpp/ublox_msgs/msg/detail/nav_timegps__rosidl_typesupport_introspection_cpp.hpp",
			"sourceGroupIndex" : 0
		},
		{
			"backtrace" : 5,
			"isGenerated" : true,
			"path" : "/home/scv/SCV/build/ublox_msgs/rosidl_typesupport_introspection_cpp/ublox_msgs/msg/detail/nav_timeutc__rosidl_typesupport_introspection_cpp.hpp",
			"sourceGroupIndex" : 0
		},
		{
			"backtrace" : 5,
			"isGenerated" : true,
			"path" : "/home/scv/SCV/build/ublox_msgs/rosidl_typesupport_introspection_cpp/ublox_msgs/msg/detail/nav_velecef__rosidl_typesupport_introspection_cpp.hpp",
			"sourceGroupIndex" : 0
		},
		{
			"backtrace" : 5,
			"isGenerated" : true,
			"path" : "/home/scv/SCV/build/ublox_msgs/rosidl_typesupport_introspection_cpp/ublox_msgs/msg/detail/nav_velned__rosidl_typesupport_introspection_cpp.hpp",
			"sourceGroupIndex" : 0
		},
		{
			"backtrace" : 5,
			"isGenerated" : true,
			"path" : "/home/scv/SCV/build/ublox_msgs/rosidl_typesupport_introspection_cpp/ublox_msgs/msg/detail/rxm_alm__rosidl_typesupport_introspection_cpp.hpp",
			"sourceGroupIndex" : 0
		},
		{
			"backtrace" : 5,
			"isGenerated" : true,
			"path" : "/home/scv/SCV/build/ublox_msgs/rosidl_typesupport_introspection_cpp/ublox_msgs/msg/detail/rxm_eph__rosidl_typesupport_introspection_cpp.hpp",
			"sourceGroupIndex" : 0
		},
		{
			"backtrace" : 5,
			"isGenerated" : true,
			"path" : "/home/scv/SCV/build/ublox_msgs/rosidl_typesupport_introspection_cpp/ublox_msgs/msg/detail/rxm_raw__rosidl_typesupport_introspection_cpp.hpp",
			"sourceGroupIndex" : 0
		},
		{
			"backtrace" : 5,
			"isGenerated" : true,
			"path" : "/home/scv/SCV/build/ublox_msgs/rosidl_typesupport_introspection_cpp/ublox_msgs/msg/detail/rxm_rawsv__rosidl_typesupport_introspection_cpp.hpp",
			"sourceGroupIndex" : 0
		},
		{
			"backtrace" : 5,
			"isGenerated" : true,
			"path" : "/home/scv/SCV/build/ublox_msgs/rosidl_typesupport_introspection_cpp/ublox_msgs/msg/detail/rxm_rawx_meas__rosidl_typesupport_introspection_cpp.hpp",
			"sourceGroupIndex" : 0
		},
		{
			"backtrace" : 5,
			"isGenerated" : true,
			"path" : "/home/scv/SCV/build/ublox_msgs/rosidl_typesupport_introspection_cpp/ublox_msgs/msg/detail/rxm_rawx__rosidl_typesupport_introspection_cpp.hpp",
			"sourceGroupIndex" : 0
		},
		{
			"backtrace" : 5,
			"isGenerated" : true,
			"path" : "/home/scv/SCV/build/ublox_msgs/rosidl_typesupport_introspection_cpp/ublox_msgs/msg/detail/rxm_rtcm__rosidl_typesupport_introspection_cpp.hpp",
			"sourceGroupIndex" : 0
		},
		{
			"backtrace" : 5,
			"isGenerated" : true,
			"path" : "/home/scv/SCV/build/ublox_msgs/rosidl_typesupport_introspection_cpp/ublox_msgs/msg/detail/rxm_sfrb__rosidl_typesupport_introspection_cpp.hpp",
			"sourceGroupIndex" : 0
		},
		{
			"backtrace" : 5,
			"isGenerated" : true,
			"path" : "/home/scv/SCV/build/ublox_msgs/rosidl_typesupport_introspection_cpp/ublox_msgs/msg/detail/rxm_sfrbx__rosidl_typesupport_introspection_cpp.hpp",
			"sourceGroupIndex" : 0
		},
		{
			"backtrace" : 5,
			"isGenerated" : true,
			"path" : "/home/scv/SCV/build/ublox_msgs/rosidl_typesupport_introspection_cpp/ublox_msgs/msg/detail/rxm_svsi__rosidl_typesupport_introspection_cpp.hpp",
			"sourceGroupIndex" : 0
		},
		{
			"backtrace" : 5,
			"isGenerated" : true,
			"path" : "/home/scv/SCV/build/ublox_msgs/rosidl_typesupport_introspection_cpp/ublox_msgs/msg/detail/rxm_svsisv__rosidl_typesupport_introspection_cpp.hpp",
			"sourceGroupIndex" : 0
		},
		{
			"backtrace" : 5,
			"isGenerated" : true,
			"path" : "/home/scv/SCV/build/ublox_msgs/rosidl_typesupport_introspection_cpp/ublox_msgs/msg/detail/tim_tm2__rosidl_typesupport_introspection_cpp.hpp",
			"sourceGroupIndex" : 0
		},
		{
			"backtrace" : 5,
			"isGenerated" : true,
			"path" : "/home/scv/SCV/build/ublox_msgs/rosidl_typesupport_introspection_cpp/ublox_msgs/msg/detail/upd_sos_ack__rosidl_typesupport_introspection_cpp.hpp",
			"sourceGroupIndex" : 0
		},
		{
			"backtrace" : 5,
			"isGenerated" : true,
			"path" : "/home/scv/SCV/build/ublox_msgs/rosidl_typesupport_introspection_cpp/ublox_msgs/msg/detail/upd_sos__rosidl_typesupport_introspection_cpp.hpp",
			"sourceGroupIndex" : 0
		},
		{
			"backtrace" : 5,
			"compileGroupIndex" : 0,
			"isGenerated" : true,
			"path" : "/home/scv/SCV/build/ublox_msgs/rosidl_typesupport_introspection_cpp/ublox_msgs/msg/detail/ack__type_support.cpp",
			"sourceGroupIndex" : 1
		},
		{
			"backtrace" : 5,
			"compileGroupIndex" : 0,
			"isGenerated" : true,
			"path" : "/home/scv/SCV/build/ublox_msgs/rosidl_typesupport_introspection_cpp/ublox_msgs/msg/detail/aid_alm__type_support.cpp",
			"sourceGroupIndex" : 1
		},
		{
			"backtrace" : 5,
			"compileGroupIndex" : 0,
			"isGenerated" : true,
			"path" : "/home/scv/SCV/build/ublox_msgs/rosidl_typesupport_introspection_cpp/ublox_msgs/msg/detail/aid_eph__type_support.cpp",
			"sourceGroupIndex" : 1
		},
		{
			"backtrace" : 5,
			"compileGroupIndex" : 0,
			"isGenerated" : true,
			"path" : "/home/scv/SCV/build/ublox_msgs/rosidl_typesupport_introspection_cpp/ublox_msgs/msg/detail/aid_hui__type_support.cpp",
			"sourceGroupIndex" : 1
		},
		{
			"backtrace" : 5,
			"compileGroupIndex" : 0,
			"isGenerated" : true,
			"path" : "/home/scv/SCV/build/ublox_msgs/rosidl_typesupport_introspection_cpp/ublox_msgs/msg/detail/cfg_ant__type_support.cpp",
			"sourceGroupIndex" : 1
		},
		{
			"backtrace" : 5,
			"compileGroupIndex" : 0,
			"isGenerated" : true,
			"path" : "/home/scv/SCV/build/ublox_msgs/rosidl_typesupport_introspection_cpp/ublox_msgs/msg/detail/cfg_cfg__type_support.cpp",
			"sourceGroupIndex" : 1
		},
		{
			"backtrace" : 5,
			"compileGroupIndex" : 0,
			"isGenerated" : true,
			"path" : "/home/scv/SCV/build/ublox_msgs/rosidl_typesupport_introspection_cpp/ublox_msgs/msg/detail/cfg_dat__type_support.cpp",
			"sourceGroupIndex" : 1
		},
		{
			"backtrace" : 5,
			"compileGroupIndex" : 0,
			"isGenerated" : true,
			"path" : "/home/scv/SCV/build/ublox_msgs/rosidl_typesupport_introspection_cpp/ublox_msgs/msg/detail/cfg_dgnss__type_support.cpp",
			"sourceGroupIndex" : 1
		},
		{
			"backtrace" : 5,
			"compileGroupIndex" : 0,
			"isGenerated" : true,
			"path" : "/home/scv/SCV/build/ublox_msgs/rosidl_typesupport_introspection_cpp/ublox_msgs/msg/detail/cfg_gnss_block__type_support.cpp",
			"sourceGroupIndex" : 1
		},
		{
			"backtrace" : 5,
			"compileGroupIndex" : 0,
			"isGenerated" : true,
			"path" : "/home/scv/SCV/build/ublox_msgs/rosidl_typesupport_introspection_cpp/ublox_msgs/msg/detail/cfg_gnss__type_support.cpp",
			"sourceGroupIndex" : 1
		},
		{
			"backtrace" : 5,
			"compileGroupIndex" : 0,
			"isGenerated" : true,
			"path" : "/home/scv/SCV/build/ublox_msgs/rosidl_typesupport_introspection_cpp/ublox_msgs/msg/detail/cfg_hnr__type_support.cpp",
			"sourceGroupIndex" : 1
		},
		{
			"backtrace" : 5,
			"compileGroupIndex" : 0,
			"isGenerated" : true,
			"path" : "/home/scv/SCV/build/ublox_msgs/rosidl_typesupport_introspection_cpp/ublox_msgs/msg/detail/cfg_inf_block__type_support.cpp",
			"sourceGroupIndex" : 1
		},
		{
			"backtrace" : 5,
			"compileGroupIndex" : 0,
			"isGenerated" : true,
			"path" : "/home/scv/SCV/build/ublox_msgs/rosidl_typesupport_introspection_cpp/ublox_msgs/msg/detail/cfg_inf__type_support.cpp",
			"sourceGroupIndex" : 1
		},
		{
			"backtrace" : 5,
			"compileGroupIndex" : 0,
			"isGenerated" : true,
			"path" : "/home/scv/SCV/build/ublox_msgs/rosidl_typesupport_introspection_cpp/ublox_msgs/msg/detail/cfg_msg__type_support.cpp",
			"sourceGroupIndex" : 1
		},
		{
			"backtrace" : 5,
			"compileGroupIndex" : 0,
			"isGenerated" : true,
			"path" : "/home/scv/SCV/build/ublox_msgs/rosidl_typesupport_introspection_cpp/ublox_msgs/msg/detail/cfg_nav5__type_support.cpp",
			"sourceGroupIndex" : 1
		},
		{
			"backtrace" : 5,
			"compileGroupIndex" : 0,
			"isGenerated" : true,
			"path" : "/home/scv/SCV/build/ublox_msgs/rosidl_typesupport_introspection_cpp/ublox_msgs/msg/detail/cfg_navx5__type_support.cpp",
			"sourceGroupIndex" : 1
		},
		{
			"backtrace" : 5,
			"compileGroupIndex" : 0,
			"isGenerated" : true,
			"path" : "/home/scv/SCV/build/ublox_msgs/rosidl_typesupport_introspection_cpp/ublox_msgs/msg/detail/cfg_nmea6__type_support.cpp",
			"sourceGroupIndex" : 1
		},
		{
			"backtrace" : 5,
			"compileGroupIndex" : 0,
			"isGenerated" : true,
			"path" : "/home/scv/SCV/build/ublox_msgs/rosidl_typesupport_introspection_cpp/ublox_msgs/msg/detail/cfg_nmea7__type_support.cpp",
			"sourceGroupIndex" : 1
		},
		{
			"backtrace" : 5,
			"compileGroupIndex" : 0,
			"isGenerated" : true,
			"path" : "/home/scv/SCV/build/ublox_msgs/rosidl_typesupport_introspection_cpp/ublox_msgs/msg/detail/cfg_nmea__type_support.cpp",
			"sourceGroupIndex" : 1
		},
		{
			"backtrace" : 5,
			"compileGroupIndex" : 0,
			"isGenerated" : true,
			"path" : "/home/scv/SCV/build/ublox_msgs/rosidl_typesupport_introspection_cpp/ublox_msgs/msg/detail/cfg_prt__type_support.cpp",
			"sourceGroupIndex" : 1
		},
		{
			"backtrace" : 5,
			"compileGroupIndex" : 0,
			"isGenerated" : true,
			"path" : "/home/scv/SCV/build/ublox_msgs/rosidl_typesupport_introspection_cpp/ublox_msgs/msg/detail/cfg_rate__type_support.cpp",
			"sourceGroupIndex" : 1
		},
		{
			"backtrace" : 5,
			"compileGroupIndex" : 0,
			"isGenerated" : true,
			"path" : "/home/scv/SCV/build/ublox_msgs/rosidl_typesupport_introspection_cpp/ublox_msgs/msg/detail/cfg_rst__type_support.cpp",
			"sourceGroupIndex" : 1
		},
		{
			"backtrace" : 5,
			"compileGroupIndex" : 0,
			"isGenerated" : true,
			"path" : "/home/scv/SCV/build/ublox_msgs/rosidl_typesupport_introspection_cpp/ublox_msgs/msg/detail/cfg_sbas__type_support.cpp",
			"sourceGroupIndex" : 1
		},
		{
			"backtrace" : 5,
			"compileGroupIndex" : 0,
			"isGenerated" : true,
			"path" : "/home/scv/SCV/build/ublox_msgs/rosidl_typesupport_introspection_cpp/ublox_msgs/msg/detail/cfg_tmode3__type_support.cpp",
			"sourceGroupIndex" : 1
		},
		{
			"backtrace" : 5,
			"compileGroupIndex" : 0,
			"isGenerated" : true,
			"path" : "/home/scv/SCV/build/ublox_msgs/rosidl_typesupport_introspection_cpp/ublox_msgs/msg/detail/cfg_usb__type_support.cpp",
			"sourceGroupIndex" : 1
		},
		{
			"backtrace" : 5,
			"compileGroupIndex" : 0,
			"isGenerated" : true,
			"path" : "/home/scv/SCV/build/ublox_msgs/rosidl_typesupport_introspection_cpp/ublox_msgs/msg/detail/cfg_valdel__type_support.cpp",
			"sourceGroupIndex" : 1
		},
		{
			"backtrace" : 5,
			"compileGroupIndex" : 0,
			"isGenerated" : true,
			"path" : "/home/scv/SCV/build/ublox_msgs/rosidl_typesupport_introspection_cpp/ublox_msgs/msg/detail/cfg_valget__type_support.cpp",
			"sourceGroupIndex" : 1
		},
		{
			"backtrace" : 5,
			"compileGroupIndex" : 0,
			"isGenerated" : true,
			"path" : "/home/scv/SCV/build/ublox_msgs/rosidl_typesupport_introspection_cpp/ublox_msgs/msg/detail/cfg_valset__type_support.cpp",
			"sourceGroupIndex" : 1
		},
		{
			"backtrace" : 5,
			"compileGroupIndex" : 0,
			"isGenerated" : true,
			"path" : "/home/scv/SCV/build/ublox_msgs/rosidl_typesupport_introspection_cpp/ublox_msgs/msg/detail/cfg_valset_cfgdata__type_support.cpp",
			"sourceGroupIndex" : 1
		},
		{
			"backtrace" : 5,
			"compileGroupIndex" : 0,
			"isGenerated" : true,
			"path" : "/home/scv/SCV/build/ublox_msgs/rosidl_typesupport_introspection_cpp/ublox_msgs/msg/detail/esf_ins__type_support.cpp",
			"sourceGroupIndex" : 1
		},
		{
			"backtrace" : 5,
			"compileGroupIndex" : 0,
			"isGenerated" : true,
			"path" : "/home/scv/SCV/build/ublox_msgs/rosidl_typesupport_introspection_cpp/ublox_msgs/msg/detail/esf_meas__type_support.cpp",
			"sourceGroupIndex" : 1
		},
		{
			"backtrace" : 5,
			"compileGroupIndex" : 0,
			"isGenerated" : true,
			"path" : "/home/scv/SCV/build/ublox_msgs/rosidl_typesupport_introspection_cpp/ublox_msgs/msg/detail/esf_raw_block__type_support.cpp",
			"sourceGroupIndex" : 1
		},
		{
			"backtrace" : 5,
			"compileGroupIndex" : 0,
			"isGenerated" : true,
			"path" : "/home/scv/SCV/build/ublox_msgs/rosidl_typesupport_introspection_cpp/ublox_msgs/msg/detail/esf_raw__type_support.cpp",
			"sourceGroupIndex" : 1
		},
		{
			"backtrace" : 5,
			"compileGroupIndex" : 0,
			"isGenerated" : true,
			"path" : "/home/scv/SCV/build/ublox_msgs/rosidl_typesupport_introspection_cpp/ublox_msgs/msg/detail/esf_status__type_support.cpp",
			"sourceGroupIndex" : 1
		},
		{
			"backtrace" : 5,
			"compileGroupIndex" : 0,
			"isGenerated" : true,
			"path" : "/home/scv/SCV/build/ublox_msgs/rosidl_typesupport_introspection_cpp/ublox_msgs/msg/detail/esf_status_sens__type_support.cpp",
			"sourceGroupIndex" : 1
		},
		{
			"backtrace" : 5,
			"compileGroupIndex" : 0,
			"isGenerated" : true,
			"path" : "/home/scv/SCV/build/ublox_msgs/rosidl_typesupport_introspection_cpp/ublox_msgs/msg/detail/hnr_pvt__type_support.cpp",
			"sourceGroupIndex" : 1
		},
		{
			"backtrace" : 5,
			"compileGroupIndex" : 0,
			"isGenerated" : true,
			"path" : "/home/scv/SCV/build/ublox_msgs/rosidl_typesupport_introspection_cpp/ublox_msgs/msg/detail/inf__type_support.cpp",
			"sourceGroupIndex" : 1
		},
		{
			"backtrace" : 5,
			"compileGroupIndex" : 0,
			"isGenerated" : true,
			"path" : "/home/scv/SCV/build/ublox_msgs/rosidl_typesupport_introspection_cpp/ublox_msgs/msg/detail/mga_gal__type_support.cpp",
			"sourceGroupIndex" : 1
		},
		{
			"backtrace" : 5,
			"compileGroupIndex" : 0,
			"isGenerated" : true,
			"path" : "/home/scv/SCV/build/ublox_msgs/rosidl_typesupport_introspection_cpp/ublox_msgs/msg/detail/mon_gnss__type_support.cpp",
			"sourceGroupIndex" : 1
		},
		{
			"backtrace" : 5,
			"compileGroupIndex" : 0,
			"isGenerated" : true,
			"path" : "/home/scv/SCV/build/ublox_msgs/rosidl_typesupport_introspection_cpp/ublox_msgs/msg/detail/mon_hw6__type_support.cpp",
			"sourceGroupIndex" : 1
		},
		{
			"backtrace" : 5,
			"compileGroupIndex" : 0,
			"isGenerated" : true,
			"path" : "/home/scv/SCV/build/ublox_msgs/rosidl_typesupport_introspection_cpp/ublox_msgs/msg/detail/mon_hw__type_support.cpp",
			"sourceGroupIndex" : 1
		},
		{
			"backtrace" : 5,
			"compileGroupIndex" : 0,
			"isGenerated" : true,
			"path" : "/home/scv/SCV/build/ublox_msgs/rosidl_typesupport_introspection_cpp/ublox_msgs/msg/detail/mon_ver_extension__type_support.cpp",
			"sourceGroupIndex" : 1
		},
		{
			"backtrace" : 5,
			"compileGroupIndex" : 0,
			"isGenerated" : true,
			"path" : "/home/scv/SCV/build/ublox_msgs/rosidl_typesupport_introspection_cpp/ublox_msgs/msg/detail/mon_ver__type_support.cpp",
			"sourceGroupIndex" : 1
		},
		{
			"backtrace" : 5,
			"compileGroupIndex" : 0,
			"isGenerated" : true,
			"path" : "/home/scv/SCV/build/ublox_msgs/rosidl_typesupport_introspection_cpp/ublox_msgs/msg/detail/nav_att__type_support.cpp",
			"sourceGroupIndex" : 1
		},
		{
			"backtrace" : 5,
			"compileGroupIndex" : 0,
			"isGenerated" : true,
			"path" : "/home/scv/SCV/build/ublox_msgs/rosidl_typesupport_introspection_cpp/ublox_msgs/msg/detail/nav_clock__type_support.cpp",
			"sourceGroupIndex" : 1
		},
		{
			"backtrace" : 5,
			"compileGroupIndex" : 0,
			"isGenerated" : true,
			"path" : "/home/scv/SCV/build/ublox_msgs/rosidl_typesupport_introspection_cpp/ublox_msgs/msg/detail/nav_cov__type_support.cpp",
			"sourceGroupIndex" : 1
		},
		{
			"backtrace" : 5,
			"compileGroupIndex" : 0,
			"isGenerated" : true,
			"path" : "/home/scv/SCV/build/ublox_msgs/rosidl_typesupport_introspection_cpp/ublox_msgs/msg/detail/nav_dgps__type_support.cpp",
			"sourceGroupIndex" : 1
		},
		{
			"backtrace" : 5,
			"compileGroupIndex" : 0,
			"isGenerated" : true,
			"path" : "/home/scv/SCV/build/ublox_msgs/rosidl_typesupport_introspection_cpp/ublox_msgs/msg/detail/nav_dgpssv__type_support.cpp",
			"sourceGroupIndex" : 1
		},
		{
			"backtrace" : 5,
			"compileGroupIndex" : 0,
			"isGenerated" : true,
			"path" : "/home/scv/SCV/build/ublox_msgs/rosidl_typesupport_introspection_cpp/ublox_msgs/msg/detail/nav_dop__type_support.cpp",
			"sourceGroupIndex" : 1
		},
		{
			"backtrace" : 5,
			"compileGroupIndex" : 0,
			"isGenerated" : true,
			"path" : "/home/scv/SCV/build/ublox_msgs/rosidl_typesupport_introspection_cpp/ublox_msgs/msg/detail/nav_posecef__type_support.cpp",
			"sourceGroupIndex" : 1
		},
		{
			"backtrace" : 5,
			"compileGroupIndex" : 0,
			"isGenerated" : true,
			"path" : "/home/scv/SCV/build/ublox_msgs/rosidl_typesupport_introspection_cpp/ublox_msgs/msg/detail/nav_posllh__type_support.cpp",
			"sourceGroupIndex" : 1
		},
		{
			"backtrace" : 5,
			"compileGroupIndex" : 0,
			"isGenerated" : true,
			"path" : "/home/scv/SCV/build/ublox_msgs/rosidl_typesupport_introspection_cpp/ublox_msgs/msg/detail/nav_pvt7__type_support.cpp",
			"sourceGroupIndex" : 1
		},
		{
			"backtrace" : 5,
			"compileGroupIndex" : 0,
			"isGenerated" : true,
			"path" : "/home/scv/SCV/build/ublox_msgs/rosidl_typesupport_introspection_cpp/ublox_msgs/msg/detail/nav_pvt__type_support.cpp",
			"sourceGroupIndex" : 1
		},
		{
			"backtrace" : 5,
			"compileGroupIndex" : 0,
			"isGenerated" : true,
			"path" : "/home/scv/SCV/build/ublox_msgs/rosidl_typesupport_introspection_cpp/ublox_msgs/msg/detail/nav_relposned9__type_support.cpp",
			"sourceGroupIndex" : 1
		},
		{
			"backtrace" : 5,
			"compileGroupIndex" : 0,
			"isGenerated" : true,
			"path" : "/home/scv/SCV/build/ublox_msgs/rosidl_typesupport_introspection_cpp/ublox_msgs/msg/detail/nav_relposned__type_support.cpp",
			"sourceGroupIndex" : 1
		},
		{
			"backtrace" : 5,
			"compileGroupIndex" : 0,
			"isGenerated" : true,
			"path" : "/home/scv/SCV/build/ublox_msgs/rosidl_typesupport_introspection_cpp/ublox_msgs/msg/detail/nav_sat__type_support.cpp",
			"sourceGroupIndex" : 1
		},
		{
			"backtrace" : 5,
			"compileGroupIndex" : 0,
			"isGenerated" : true,
			"path" : "/home/scv/SCV/build/ublox_msgs/rosidl_typesupport_introspection_cpp/ublox_msgs/msg/detail/nav_satsv__type_support.cpp",
			"sourceGroupIndex" : 1
		},
		{
			"backtrace" : 5,
			"compileGroupIndex" : 0,
			"isGenerated" : true,
			"path" : "/home/scv/SCV/build/ublox_msgs/rosidl_typesupport_introspection_cpp/ublox_msgs/msg/detail/nav_sbas__type_support.cpp",
			"sourceGroupIndex" : 1
		},
		{
			"backtrace" : 5,
			"compileGroupIndex" : 0,
			"isGenerated" : true,
			"path" : "/home/scv/SCV/build/ublox_msgs/rosidl_typesupport_introspection_cpp/ublox_msgs/msg/detail/nav_sbassv__type_support.cpp",
			"sourceGroupIndex" : 1
		},
		{
			"backtrace" : 5,
			"compileGroupIndex" : 0,
			"isGenerated" : true,
			"path" : "/home/scv/SCV/build/ublox_msgs/rosidl_typesupport_introspection_cpp/ublox_msgs/msg/detail/nav_sol__type_support.cpp",
			"sourceGroupIndex" : 1
		},
		{
			"backtrace" : 5,
			"compileGroupIndex" : 0,
			"isGenerated" : true,
			"path" : "/home/scv/SCV/build/ublox_msgs/rosidl_typesupport_introspection_cpp/ublox_msgs/msg/detail/nav_status__type_support.cpp",
			"sourceGroupIndex" : 1
		},
		{
			"backtrace" : 5,
			"compileGroupIndex" : 0,
			"isGenerated" : true,
			"path" : "/home/scv/SCV/build/ublox_msgs/rosidl_typesupport_introspection_cpp/ublox_msgs/msg/detail/nav_svinfo__type_support.cpp",
			"sourceGroupIndex" : 1
		},
		{
			"backtrace" : 5,
			"compileGroupIndex" : 0,
			"isGenerated" : true,
			"path" : "/home/scv/SCV/build/ublox_msgs/rosidl_typesupport_introspection_cpp/ublox_msgs/msg/detail/nav_svinfosv__type_support.cpp",
			"sourceGroupIndex" : 1
		},
		{
			"backtrace" : 5,
			"compileGroupIndex" : 0,
			"isGenerated" : true,
			"path" : "/home/scv/SCV/build/ublox_msgs/rosidl_typesupport_introspection_cpp/ublox_msgs/msg/detail/nav_svin__type_support.cpp",
			"sourceGroupIndex" : 1
		},
		{
			"backtrace" : 5,
			"compileGroupIndex" : 0,
			"isGenerated" : true,
			"path" : "/home/scv/SCV/build/ublox_msgs/rosidl_typesupport_introspection_cpp/ublox_msgs/msg/detail/nav_timegps__type_support.cpp",
			"sourceGroupIndex" : 1
		},
		{
			"backtrace" : 5,
			"compileGroupIndex" : 0,
			"isGenerated" : true,
			"path" : "/home/scv/SCV/build/ublox_msgs/rosidl_typesupport_introspection_cpp/ublox_msgs/msg/detail/nav_timeutc__type_support.cpp",
			"sourceGroupIndex" : 1
		},
		{
			"backtrace" : 5,
			"compileGroupIndex" : 0,
			"isGenerated" : true,
			"path" : "/home/scv/SCV/build/ublox_msgs/rosidl_typesupport_introspection_cpp/ublox_msgs/msg/detail/nav_velecef__type_support.cpp",
			"sourceGroupIndex" : 1
		},
		{
			"backtrace" : 5,
			"compileGroupIndex" : 0,
			"isGenerated" : true,
			"path" : "/home/scv/SCV/build/ublox_msgs/rosidl_typesupport_introspection_cpp/ublox_msgs/msg/detail/nav_velned__type_support.cpp",
			"sourceGroupIndex" : 1
		},
		{
			"backtrace" : 5,
			"compileGroupIndex" : 0,
			"isGenerated" : true,
			"path" : "/home/scv/SCV/build/ublox_msgs/rosidl_typesupport_introspection_cpp/ublox_msgs/msg/detail/rxm_alm__type_support.cpp",
			"sourceGroupIndex" : 1
		},
		{
			"backtrace" : 5,
			"compileGroupIndex" : 0,
			"isGenerated" : true,
			"path" : "/home/scv/SCV/build/ublox_msgs/rosidl_typesupport_introspection_cpp/ublox_msgs/msg/detail/rxm_eph__type_support.cpp",
			"sourceGroupIndex" : 1
		},
		{
			"backtrace" : 5,
			"compileGroupIndex" : 0,
			"isGenerated" : true,
			"path" : "/home/scv/SCV/build/ublox_msgs/rosidl_typesupport_introspection_cpp/ublox_msgs/msg/detail/rxm_raw__type_support.cpp",
			"sourceGroupIndex" : 1
		},
		{
			"backtrace" : 5,
			"compileGroupIndex" : 0,
			"isGenerated" : true,
			"path" : "/home/scv/SCV/build/ublox_msgs/rosidl_typesupport_introspection_cpp/ublox_msgs/msg/detail/rxm_rawsv__type_support.cpp",
			"sourceGroupIndex" : 1
		},
		{
			"backtrace" : 5,
			"compileGroupIndex" : 0,
			"isGenerated" : true,
			"path" : "/home/scv/SCV/build/ublox_msgs/rosidl_typesupport_introspection_cpp/ublox_msgs/msg/detail/rxm_rawx_meas__type_support.cpp",
			"sourceGroupIndex" : 1
		},
		{
			"backtrace" : 5,
			"compileGroupIndex" : 0,
			"isGenerated" : true,
			"path" : "/home/scv/SCV/build/ublox_msgs/rosidl_typesupport_introspection_cpp/ublox_msgs/msg/detail/rxm_rawx__type_support.cpp",
			"sourceGroupIndex" : 1
		},
		{
			"backtrace" : 5,
			"compileGroupIndex" : 0,
			"isGenerated" : true,
			"path" : "/home/scv/SCV/build/ublox_msgs/rosidl_typesupport_introspection_cpp/ublox_msgs/msg/detail/rxm_rtcm__type_support.cpp",
			"sourceGroupIndex" : 1
		},
		{
			"backtrace" : 5,
			"compileGroupIndex" : 0,
			"isGenerated" : true,
			"path" : "/home/scv/SCV/build/ublox_msgs/rosidl_typesupport_introspection_cpp/ublox_msgs/msg/detail/rxm_sfrb__type_support.cpp",
			"sourceGroupIndex" : 1
		},
		{
			"backtrace" : 5,
			"compileGroupIndex" : 0,
			"isGenerated" : true,
			"path" : "/home/scv/SCV/build/ublox_msgs/rosidl_typesupport_introspection_cpp/ublox_msgs/msg/detail/rxm_sfrbx__type_support.cpp",
			"sourceGroupIndex" : 1
		},
		{
			"backtrace" : 5,
			"compileGroupIndex" : 0,
			"isGenerated" : true,
			"path" : "/home/scv/SCV/build/ublox_msgs/rosidl_typesupport_introspection_cpp/ublox_msgs/msg/detail/rxm_svsi__type_support.cpp",
			"sourceGroupIndex" : 1
		},
		{
			"backtrace" : 5,
			"compileGroupIndex" : 0,
			"isGenerated" : true,
			"path" : "/home/scv/SCV/build/ublox_msgs/rosidl_typesupport_introspection_cpp/ublox_msgs/msg/detail/rxm_svsisv__type_support.cpp",
			"sourceGroupIndex" : 1
		},
		{
			"backtrace" : 5,
			"compileGroupIndex" : 0,
			"isGenerated" : true,
			"path" : "/home/scv/SCV/build/ublox_msgs/rosidl_typesupport_introspection_cpp/ublox_msgs/msg/detail/tim_tm2__type_support.cpp",
			"sourceGroupIndex" : 1
		},
		{
			"backtrace" : 5,
			"compileGroupIndex" : 0,
			"isGenerated" : true,
			"path" : "/home/scv/SCV/build/ublox_msgs/rosidl_typesupport_introspection_cpp/ublox_msgs/msg/detail/upd_sos_ack__type_support.cpp",
			"sourceGroupIndex" : 1
		},
		{
			"backtrace" : 5,
			"compileGroupIndex" : 0,
			"isGenerated" : true,
			"path" : "/home/scv/SCV/build/ublox_msgs/rosidl_typesupport_introspection_cpp/ublox_msgs/msg/detail/upd_sos__type_support.cpp",
			"sourceGroupIndex" : 1
		},
		{
			"backtrace" : 0,
			"isGenerated" : true,
			"path" : "/home/scv/SCV/build/ublox_msgs/rosidl_typesupport_introspection_cpp/ublox_msgs/msg/detail/ack__rosidl_typesupport_introspection_cpp.hpp.rule",
			"sourceGroupIndex" : 2
		}
	],
	"type" : "SHARED_LIBRARY"
}
